clearcache
